showinfm/__about__.py
showinfm/__init__.py
showinfm/argumentsparse.py
showinfm/constants.py
showinfm/filemanager.py
showinfm/py.typed
showinfm/showinfm.py
showinfm/system/__init__.py
showinfm/system/linux.py
showinfm/system/tools.py
showinfm/system/urivalidate.py
showinfm/system/windows.py
je_showinfilemanager-1.1.6a4.dist-info/METADATA
je_showinfilemanager-1.1.6a4.dist-info/WHEEL
je_showinfilemanager-1.1.6a4.dist-info/entry_points.txt
je_showinfilemanager-1.1.6a4.dist-info/licenses/LICENSE
je_showinfilemanager-1.1.6a4.dist-info/RECORD
