Metadata-Version: 2.4
Name: je-showinfilemanager
Version: 1.1.6a4
Summary: Open the system file manager and select files in it
Project-URL: Homepage, https://github.com/damonlynch/showinfilemanager
Project-URL: Issues, https://github.com/damonlynch/showinfilemanager/issues
Author-email: Damon Lynch <damonlynch@gmail.com>
License-File: LICENSE
Classifier: Development Status :: 5 - Production/Stable
Classifier: License :: OSI Approved :: MIT License
Classifier: Operating System :: MacOS :: MacOS X
Classifier: Operating System :: Microsoft :: Windows :: Windows 10
Classifier: Operating System :: Microsoft :: Windows :: Windows 11
Classifier: Operating System :: POSIX :: Linux
Classifier: Programming Language :: Python :: 3.8
Classifier: Programming Language :: Python :: 3.9
Classifier: Programming Language :: Python :: 3.10
Classifier: Programming Language :: Python :: 3.11
Classifier: Programming Language :: Python :: 3.12
Classifier: Topic :: Desktop Environment :: File Managers
Classifier: Typing :: Typed
Requires-Python: >=3.8
Requires-Dist: packaging
Requires-Dist: pywin32>=301; platform_system == 'Windows'
Requires-Dist: pyxdg>=0.25; platform_system == 'Linux'
